[
    {
        "id": "Branding",
        "author": "Featly",
        "width": 5616,
        "height": 3744,
        "url": "images/featly-logo.gif",
        "download_url": "images/featly-logo.gif",
        "path": "/detail"
    },
    {
        "id": "Computational design",
        "author": "Handpicked Labs",
        "width": 5616,
        "height": 3744,
        "url": "images/Mobiel-Handpicked.png",
        "download_url": "images/Mobiel-Handpicked.png",
        "path": "/detail"
    },
    {
        "id": "YouTube header",
        "author": "Velum",
        "width": 2500,
        "height": 1667,
        "url": "http://maikimmers.nl/wp-content/gallery/test/Velum-New-youtube-Layout.png",
        "download_url": "http://maikimmers.nl/wp-content/gallery/test/Velum-New-youtube-Layout.png",
        "path": "/detail"
    },
    {
        "id": "Concept logo",
        "author": "Dreamon",
        "width": 2500,
        "height": 1656,
        "url": "images/dreamon-banner.jpg",
        "download_url": "images/dreamon-banner.jpg",
        "path": "/"
    },
    {
        "id": "1000",
        "author": "Lukas Budimaier",
        "width": 5626,
        "height": 3635,
        "url": "images/theresia-banner.jpg",
        "download_url": "images/theresia-banner.jpg",
        "path": "/"
    },
    {
        "id": "1001",
        "author": "Danielle MacInnes",
        "width": 5616,
        "height": 3744,
        "url": "https://unsplash.com/photos/1DkWWN1dr-s",
        "download_url": "https://picsum.photos/id/1001/5616/3744",
        "path": "/"
    },
    {
        "id": "1002",
        "author": "NASA",
        "width": 4312,
        "height": 2868,
        "url": "https://unsplash.com/photos/6-jTZysYY_U",
        "download_url": "https://picsum.photos/id/1002/4312/2868",
        "path": "/"
    },
    {
        "id": "1003",
        "author": "E+N Photographies",
        "width": 1181,
        "height": 1772,
        "url": "https://unsplash.com/photos/GYumuBnTqKc",
        "download_url": "https://picsum.photos/id/1003/1181/1772",
        "path": "/"
    },
    {
        "id": "1004",
        "author": "Greg Rakozy",
        "width": 5616,
        "height": 3744,
        "url": "https://unsplash.com/photos/SSxIGsySh8o",
        "download_url": "https://picsum.photos/id/1004/5616/3744",
        "path": "/"
    },
    {
        "id": "1005",
        "author": "Matthew Wiebe",
        "width": 5760,
        "height": 3840,
        "url": "https://unsplash.com/photos/tBtuxtLvAZs",
        "download_url": "https://picsum.photos/id/1005/5760/3840",
        "path": "/"
    },
    {
        "id": "1006",
        "author": "Vladimir Kudinov",
        "width": 3000,
        "height": 2000,
        "url": "https://unsplash.com/photos/-wWRHIUklxM",
        "download_url": "https://picsum.photos/id/1006/3000/2000",
        "path": "/"
    },
    {
        "id": "1008",
        "author": "Benjamin Combs",
        "width": 5616,
        "height": 3744,
        "url": "https://unsplash.com/photos/5L4XAgMSno0",
        "download_url": "https://picsum.photos/id/1008/5616/3744",
        "path": "/"
    }
]